{"title":"HardcoreGangbang Draven Star XXX 720p 16.05.11","uid":14606589,"size":2156255742,"categoryP":"porn","categoryS":"hd___movies","magnet":"?xt=urn:btih:0228616eab43382eb2cb1f2e9b17e993c68d42cb&amp;dn=HardcoreGangbang+Draven+Star+XXX+720p+16.05.11&amp;tr=udp%3A%2F%2Ftracker.leechers-paradise.org%3A6969&amp;tr=udp%3A%2F%2Fzer0day.ch%3A1337&amp;tr=udp%3A%2F%2Fopen.demonii.com%3A1337&amp;tr=udp%3A%2F%2Ftracker.coppersurfer.tk%3A6969&amp;tr=udp%3A%2F%2Fexodus.desync.com%3A6969","seeders":0,"leechers":1,"uploader":"thfatboys","files":1,"time":1463100333,"description":"Screens: \nhttp://imgpeak.com/img-5734f3c1ebf42.html","torrent":{"xt":"urn:btih:0228616eab43382eb2cb1f2e9b17e993c68d42cb","amp;dn":"HardcoreGangbang+Draven+Star+XXX+720p+16.05.11","amp;tr":["udp%3A%2F%2Ftracker.leechers-paradise.org%3A6969","udp%3A%2F%2Fzer0day.ch%3A1337","udp%3A%2F%2Fopen.demonii.com%3A1337","udp%3A%2F%2Ftracker.coppersurfer.tk%3A6969","udp%3A%2F%2Fexodus.desync.com%3A6969"],"infoHash":"0228616eab43382eb2cb1f2e9b17e993c68d42cb","infoHashBuffer":{"type":"Buffer","data":[2,40,97,110,171,67,56,46,178,203,31,46,155,23,233,147,198,141,66,203]},"announce":[],"urlList":[]}}