{"title":"HardX Naomi Woods What Daddy Knows XXX 1080p 16.02.05","uid":13444450,"size":603199903,"categoryP":"porn","categoryS":"hd___movies","magnet":"?xt=urn:btih:0f6b9e16b30de6908a89bae5d068074d3cf5ab4f&amp;dn=HardX+Naomi+Woods+What+Daddy+Knows+XXX+1080p+16.02.05&amp;tr=udp%3A%2F%2Ftracker.leechers-paradise.org%3A6969&amp;tr=udp%3A%2F%2Fzer0day.ch%3A1337&amp;tr=udp%3A%2F%2Fopen.demonii.com%3A1337&amp;tr=udp%3A%2F%2Ftracker.coppersurfer.tk%3A6969&amp;tr=udp%3A%2F%2Fexodus.desync.com%3A6969","seeders":0,"leechers":0,"uploader":"thfatboys","files":1,"time":1454732183,"description":"Screens: \nhttp://imgpeak.com/img-56b51839c2ae4.html","torrent":{"xt":"urn:btih:0f6b9e16b30de6908a89bae5d068074d3cf5ab4f","amp;dn":"HardX+Naomi+Woods+What+Daddy+Knows+XXX+1080p+16.02.05","amp;tr":["udp%3A%2F%2Ftracker.leechers-paradise.org%3A6969","udp%3A%2F%2Fzer0day.ch%3A1337","udp%3A%2F%2Fopen.demonii.com%3A1337","udp%3A%2F%2Ftracker.coppersurfer.tk%3A6969","udp%3A%2F%2Fexodus.desync.com%3A6969"],"infoHash":"0f6b9e16b30de6908a89bae5d068074d3cf5ab4f","infoHashBuffer":{"type":"Buffer","data":[15,107,158,22,179,13,230,144,138,137,186,229,208,104,7,77,60,245,171,79]},"announce":[],"urlList":[]}}