{"title":"Garden News - February 13th 2016","uid":13479294,"size":24342881,"categoryP":"other","categoryS":"e_books","magnet":"?xt=urn:btih:11f9773943275c6aa4df0676deaf181fc41740df&amp;dn=Garden+News+-+February+13th+2016&amp;tr=udp%3A%2F%2Ftracker.leechers-paradise.org%3A6969&amp;tr=udp%3A%2F%2Fzer0day.ch%3A1337&amp;tr=udp%3A%2F%2Fopen.demonii.com%3A1337&amp;tr=udp%3A%2F%2Ftracker.coppersurfer.tk%3A6969&amp;tr=udp%3A%2F%2Fexodus.desync.com%3A6969","seeders":0,"leechers":0,"uploader":"Orangie2Dope","files":1,"time":1455044627,"description":"English | 68 pages | PDF | 23.2 Mb\r\n\r\nMake your garden great! Garden News is the magazine for every gardener, bringing you everything you need to know about YOUR garden, each week.\r\nEach issue is packed full of:\r\n- Practical, down-to-earth gardening tips\r\n- Grow-your-own advice\r\n- Expert guides to your favourite plants\r\n- Ideas and inspirational features","torrent":{"xt":"urn:btih:11f9773943275c6aa4df0676deaf181fc41740df","amp;dn":"Garden+News+-+February+13th+2016","amp;tr":["udp%3A%2F%2Ftracker.leechers-paradise.org%3A6969","udp%3A%2F%2Fzer0day.ch%3A1337","udp%3A%2F%2Fopen.demonii.com%3A1337","udp%3A%2F%2Ftracker.coppersurfer.tk%3A6969","udp%3A%2F%2Fexodus.desync.com%3A6969"],"infoHash":"11f9773943275c6aa4df0676deaf181fc41740df","infoHashBuffer":{"type":"Buffer","data":[17,249,119,57,67,39,92,106,164,223,6,118,222,175,24,31,196,23,64,223]},"announce":[],"urlList":[]}}