{"title":"Sweet Daisy","uid":14465851,"size":133628890,"categoryP":"porn","categoryS":"movie_clips","magnet":"?xt=urn:btih:144a086a7f515a72162c1975406a3449f0c58eb9&amp;dn=Sweet+Daisy&amp;tr=udp%3A%2F%2Ftracker.leechers-paradise.org%3A6969&amp;tr=udp%3A%2F%2Fzer0day.ch%3A1337&amp;tr=udp%3A%2F%2Fopen.demonii.com%3A1337&amp;tr=udp%3A%2F%2Ftracker.coppersurfer.tk%3A6969&amp;tr=udp%3A%2F%2Fexodus.desync.com%3A6969","seeders":0,"leechers":0,"uploader":"demonoidt","files":5,"time":1461855061,"description":"Samples\r\n \nhttp://adultwallpapers.co.in/sweet-daisy/\r\n \nhttp://demonoid.co/2016/04/28/sweet-daisy/","torrent":{"xt":"urn:btih:144a086a7f515a72162c1975406a3449f0c58eb9","amp;dn":"Sweet+Daisy","amp;tr":["udp%3A%2F%2Ftracker.leechers-paradise.org%3A6969","udp%3A%2F%2Fzer0day.ch%3A1337","udp%3A%2F%2Fopen.demonii.com%3A1337","udp%3A%2F%2Ftracker.coppersurfer.tk%3A6969","udp%3A%2F%2Fexodus.desync.com%3A6969"],"infoHash":"144a086a7f515a72162c1975406a3449f0c58eb9","infoHashBuffer":{"type":"Buffer","data":[20,74,8,106,127,81,90,114,22,44,25,117,64,106,52,73,240,197,142,185]},"announce":[],"urlList":[]}}