{"title":"LegalPorno - Taissia Shanti, Francsca Dicaprio - Anal Fist 720","uid":14512219,"size":2239975719,"categoryP":"porn","categoryS":"hd___movies","magnet":"?xt=urn:btih:26d84b1794749fc5c0df78a16a16e08466bf7a9c&amp;dn=LegalPorno+-+Taissia+Shanti%2C+Francsca+Dicaprio+-+Anal+Fist+720&amp;tr=udp%3A%2F%2Ftracker.leechers-paradise.org%3A6969&amp;tr=udp%3A%2F%2Fzer0day.ch%3A1337&amp;tr=udp%3A%2F%2Fopen.demonii.com%3A1337&amp;tr=udp%3A%2F%2Ftracker.coppersurfer.tk%3A6969&amp;tr=udp%3A%2F%2Fexodus.desync.com%3A6969","seeders":0,"leechers":1,"uploader":"ElitePorn","files":1,"time":1462295021,"description":"LegalPorno - Taissia Shanti, Francsca Dicaprio - Anal Fist HD 720p\r\n~~~~~~~~~~~~~~~~~~~~~~~~~~~~~~~~~~~~~~~~~~~~~~~~~~~~~~~~~~~~~~~~~~\r\n\r\nScreenshots:\r\n~~~~~~~~~~~~ \nhttp://picturescream.com/x/clean/Gp1t\r\n \nhttp://picturescream.com/x/clean/Gp1y\r\n \nhttp://picturescream.com/x/clean/Gp1z\r\n \nhttp://picturescream.com/x/clean/Gp1L\r\n \nhttp://picturescream.com/x/clean/Gp1g\r\n \nhttp://picturescream.com/x/clean/Gp1j\r\n\r\n\r\nVideos Info:\r\n~~~~~~~~~~~~\r\nSize: 2.08 GB\r\nDuration: 65 min \t\r\nResolution: 1280x720\r\n\r\n\r\nShow Your Appreciation - BitCoin: 1JxUQqRrvGC6txChvaZEbqSSsq9wtswoto","torrent":{"xt":"urn:btih:26d84b1794749fc5c0df78a16a16e08466bf7a9c","amp;dn":"LegalPorno+-+Taissia+Shanti%2C+Francsca+Dicaprio+-+Anal+Fist+720","amp;tr":["udp%3A%2F%2Ftracker.leechers-paradise.org%3A6969","udp%3A%2F%2Fzer0day.ch%3A1337","udp%3A%2F%2Fopen.demonii.com%3A1337","udp%3A%2F%2Ftracker.coppersurfer.tk%3A6969","udp%3A%2F%2Fexodus.desync.com%3A6969"],"infoHash":"26d84b1794749fc5c0df78a16a16e08466bf7a9c","infoHashBuffer":{"type":"Buffer","data":[38,216,75,23,148,116,159,197,192,223,120,161,106,22,224,132,102,191,122,156]},"announce":[],"urlList":[]}}