{"title":"Anna T (2014) SiteRip [.mp4]","uid":13012122,"size":659420320,"categoryP":"porn","categoryS":"hd___movies","magnet":"?xt=urn:btih:2c83d98e020e3be5b969af7fc6ce10b5aaf0d199&amp;dn=Anna+T+%282014%29+SiteRip+%5B.mp4%5D&amp;tr=udp%3A%2F%2Ftracker.leechers-paradise.org%3A6969&amp;tr=udp%3A%2F%2Fzer0day.ch%3A1337&amp;tr=udp%3A%2F%2Fopen.demonii.com%3A1337&amp;tr=udp%3A%2F%2Ftracker.coppersurfer.tk%3A6969&amp;tr=udp%3A%2F%2Fexodus.desync.com%3A6969","seeders":0,"leechers":1,"uploader":"MST","files":1,"time":1450263079,"description":"Anna T (2014) SiteRip [.mp4]\r\n\r\nScreens:\r\n \nhttp://www.pimpix.net/viewer.php?file=89184155470989438457.jpeg \nhttp://www.pimpix.net/viewer.php?file=40261801446866091154.jpg","torrent":{"xt":"urn:btih:2c83d98e020e3be5b969af7fc6ce10b5aaf0d199","amp;dn":"Anna+T+%282014%29+SiteRip+%5B.mp4%5D","amp;tr":["udp%3A%2F%2Ftracker.leechers-paradise.org%3A6969","udp%3A%2F%2Fzer0day.ch%3A1337","udp%3A%2F%2Fopen.demonii.com%3A1337","udp%3A%2F%2Ftracker.coppersurfer.tk%3A6969","udp%3A%2F%2Fexodus.desync.com%3A6969"],"infoHash":"2c83d98e020e3be5b969af7fc6ce10b5aaf0d199","infoHashBuffer":{"type":"Buffer","data":[44,131,217,142,2,14,59,229,185,105,175,127,198,206,16,181,170,240,209,153]},"announce":[],"urlList":[]}}