{"title":"Yanks 15 12 15 Lily Lennoxs Gets Her Vibe On XXX 1080p MP4-OHRLY","uid":13489545,"size":128063854,"categoryP":"porn","categoryS":"movie_clips","magnet":"?xt=urn:btih:33a0016b029d98694a86c293ee9efae06eb6a9fc&amp;dn=Yanks+15+12+15+Lily+Lennoxs+Gets+Her+Vibe+On+XXX+1080p+MP4-OHRLY&amp;tr=udp%3A%2F%2Ftracker.leechers-paradise.org%3A6969&amp;tr=udp%3A%2F%2Fzer0day.ch%3A1337&amp;tr=udp%3A%2F%2Fopen.demonii.com%3A1337&amp;tr=udp%3A%2F%2Ftracker.coppersurfer.tk%3A6969&amp;tr=udp%3A%2F%2Fexodus.desync.com%3A6969","seeders":0,"leechers":1,"uploader":"0-DayXXX","files":1,"time":1455110127,"description":"------------------------------------------------\nYanks.15.12.15.Lily.Lennoxs.Gets.Her.Vibe.On.XXX.1080p.MP4-OHRLY\n------------------------------------------------\nScreenshot(s): \nhttp://imgsay.com/?v=961299 \n\n------------------------------------------------\nInfo(s):\nFormat:\t\tMPEG-4\nSize:\t\t122 MiB\nDuration:\t6min 43s\nResolution:\t1920x1080\nBitrate:\t2461Kbps\n------------------------------------------------\n         ** More 0-DayXXX Uploads ** \nhttp://youpornbook.com\n------------------------------------------------\nIf you like this torrent, please post a comment!\n            Don't forget to seed!","torrent":{"xt":"urn:btih:33a0016b029d98694a86c293ee9efae06eb6a9fc","amp;dn":"Yanks+15+12+15+Lily+Lennoxs+Gets+Her+Vibe+On+XXX+1080p+MP4-OHRLY","amp;tr":["udp%3A%2F%2Ftracker.leechers-paradise.org%3A6969","udp%3A%2F%2Fzer0day.ch%3A1337","udp%3A%2F%2Fopen.demonii.com%3A1337","udp%3A%2F%2Ftracker.coppersurfer.tk%3A6969","udp%3A%2F%2Fexodus.desync.com%3A6969"],"infoHash":"33a0016b029d98694a86c293ee9efae06eb6a9fc","infoHashBuffer":{"type":"Buffer","data":[51,160,1,107,2,157,152,105,74,134,194,147,238,158,250,224,110,182,169,252]},"announce":[],"urlList":[]}}