{"title":"RealWifeStories.August.Ames.Ava.Addams","uid":14466065,"size":424232756,"categoryP":"porn","categoryS":"movie_clips","magnet":"?xt=urn:btih:3559c08350b827eeecfcdcb069ce971c5e233c2a&amp;dn=RealWifeStories.August.Ames.Ava.Addams&amp;tr=udp%3A%2F%2Ftracker.leechers-paradise.org%3A6969&amp;tr=udp%3A%2F%2Fzer0day.ch%3A1337&amp;tr=udp%3A%2F%2Fopen.demonii.com%3A1337&amp;tr=udp%3A%2F%2Ftracker.coppersurfer.tk%3A6969&amp;tr=udp%3A%2F%2Fexodus.desync.com%3A6969","seeders":0,"leechers":0,"uploader":"Piratepr0n","files":1,"time":1461857343,"description":"-------------------------------------------------------------------------------------\nName:\nRealWifeStories.August.Ames.Ava.Addams\n-------------------------------------------------------------------------------------\nFile list:\nrws.august.ava.kf082015.480p.1000.mp4 (405 MiB | 854x480 | 47min 39s | MPEG-4) \nhttp://imgfapper.com/img-5722100e53e78.html","torrent":{"xt":"urn:btih:3559c08350b827eeecfcdcb069ce971c5e233c2a","amp;dn":"RealWifeStories.August.Ames.Ava.Addams","amp;tr":["udp%3A%2F%2Ftracker.leechers-paradise.org%3A6969","udp%3A%2F%2Fzer0day.ch%3A1337","udp%3A%2F%2Fopen.demonii.com%3A1337","udp%3A%2F%2Ftracker.coppersurfer.tk%3A6969","udp%3A%2F%2Fexodus.desync.com%3A6969"],"infoHash":"3559c08350b827eeecfcdcb069ce971c5e233c2a","infoHashBuffer":{"type":"Buffer","data":[53,89,192,131,80,184,39,238,236,252,220,176,105,206,151,28,94,35,60,42]},"announce":[],"urlList":[]}}