{"title":"Bootline 1.0.1.1","uid":13317314,"size":5389312,"categoryP":"applications","categoryS":"windows","magnet":"?xt=urn:btih:4cb6cf8ef9b50dc94b63ba496b93f8b6d3d538bf&amp;dn=Bootline+1.0.1.1&amp;tr=udp%3A%2F%2Ftracker.leechers-paradise.org%3A6969&amp;tr=udp%3A%2F%2Fzer0day.ch%3A1337&amp;tr=udp%3A%2F%2Fopen.demonii.com%3A1337&amp;tr=udp%3A%2F%2Ftracker.coppersurfer.tk%3A6969&amp;tr=udp%3A%2F%2Fexodus.desync.com%3A6969","seeders":0,"leechers":0,"uploader":"BootLine","files":1,"time":1453840620,"description":"Simple, portable and lightweight tool, lets you make bootable flash drive with multiple ISO without formatting it. BootLine helps you to install Windows 7,8,10 or run live images like Kaspersky Rescue Disk or CloneZilla from your multiboot USB stick.\r\n\r\n  Your notebook with Windows or Linux onboard died? You need to rescue data, check for viruses, reinstall Windows on notebook to give it to your little sister? \r\nAll of this actions could be done without any problems with just one bootable usb with 3-4 bootloaders on board! \r\n  But creating bootable USB with several loaders may become not an easy task... And now you have to start searching for some information how to do it. \r\nYou waste time, you become tired and stressed. \r\nBootLine helps you to install Windows 7,8,10 or run live images like Kaspersky or AVG Rescue Disk, CloneZilla and other from USB stick without formatting it in a few clicks! \r\n  Bootline is portable version of web service bootline.net - you can burn your multiple ISO to flash drive online in your browser. \r\n\r\nOur advantages:   \r\n  1. Creating Multiboot USB flash drive   \r\n  2. Formatting is not required in most cases   \r\n  3. Helps to find disk images   \r\n  4. No Ads   \r\n  5. Portable app - installation not required   \r\n  6. It's possible to post message to the forum directly from app   \r\n  7. Burn images to USB drive in continuous process after choosing all\r\n\r\nOnly three steps:\r\n  1. Choose USB drive\r\n  2. Add the necessary boot loaders\r\n  3. Start burning!","torrent":{"xt":"urn:btih:4cb6cf8ef9b50dc94b63ba496b93f8b6d3d538bf","amp;dn":"Bootline+1.0.1.1","amp;tr":["udp%3A%2F%2Ftracker.leechers-paradise.org%3A6969","udp%3A%2F%2Fzer0day.ch%3A1337","udp%3A%2F%2Fopen.demonii.com%3A1337","udp%3A%2F%2Ftracker.coppersurfer.tk%3A6969","udp%3A%2F%2Fexodus.desync.com%3A6969"],"infoHash":"4cb6cf8ef9b50dc94b63ba496b93f8b6d3d538bf","infoHashBuffer":{"type":"Buffer","data":[76,182,207,142,249,181,13,201,75,99,186,73,107,147,248,182,211,213,56,191]},"announce":[],"urlList":[]}}