{"title":"The.Magicians.US.S01E04.INTERNAL.480p.x264-mSD","uid":13475587,"size":152316617,"categoryP":"video","categoryS":"tv_shows","magnet":"?xt=urn:btih:64c4c677d170ce13e6cd8ccf94d61d0f31c7fb53&amp;dn=The.Magicians.US.S01E04.INTERNAL.480p.x264-mSD&amp;tr=udp%3A%2F%2Ftracker.leechers-paradise.org%3A6969&amp;tr=udp%3A%2F%2Fzer0day.ch%3A1337&amp;tr=udp%3A%2F%2Fopen.demonii.com%3A1337&amp;tr=udp%3A%2F%2Ftracker.coppersurfer.tk%3A6969&amp;tr=udp%3A%2F%2Fexodus.desync.com%3A6969","seeders":0,"leechers":0,"uploader":"TvTeam","files":12,"time":1455007168,"description":"https://www.torrenting.com\r\n\r\nSign up is OPEN - for time being. Come and have fun.\r\n\r\n------------------------------------------------------------------------\r\n\r\nReNEW our seedbox by donating bitcoin To: 1N1qWp6Hk1REFXgJ8yviqCnLsn76BfXFh1","torrent":{"xt":"urn:btih:64c4c677d170ce13e6cd8ccf94d61d0f31c7fb53","amp;dn":"The.Magicians.US.S01E04.INTERNAL.480p.x264-mSD","amp;tr":["udp%3A%2F%2Ftracker.leechers-paradise.org%3A6969","udp%3A%2F%2Fzer0day.ch%3A1337","udp%3A%2F%2Fopen.demonii.com%3A1337","udp%3A%2F%2Ftracker.coppersurfer.tk%3A6969","udp%3A%2F%2Fexodus.desync.com%3A6969"],"infoHash":"64c4c677d170ce13e6cd8ccf94d61d0f31c7fb53","infoHashBuffer":{"type":"Buffer","data":[100,196,198,119,209,112,206,19,230,205,140,207,148,214,29,15,49,199,251,83]},"announce":[],"urlList":[]}}