{"title":"Sucktion and Ride","uid":14634797,"size":112722134,"categoryP":"porn","categoryS":"movie_clips","magnet":"?xt=urn:btih:6d8b377e6ac53c4f1bc792f62f6b5ac0daa5cf88&amp;dn=Sucktion+and+Ride&amp;tr=udp%3A%2F%2Ftracker.leechers-paradise.org%3A6969&amp;tr=udp%3A%2F%2Fzer0day.ch%3A1337&amp;tr=udp%3A%2F%2Fopen.demonii.com%3A1337&amp;tr=udp%3A%2F%2Ftracker.coppersurfer.tk%3A6969&amp;tr=udp%3A%2F%2Fexodus.desync.com%3A6969","seeders":0,"leechers":0,"uploader":"demonoidt","files":5,"time":1463426344,"description":"Samples\r\n \nhttp://adultwallpapers.co.in/sucktion-and-ride/\r\n \nhttp://demonoid.co/2016/05/16/sucktion-and-ride/","torrent":{"xt":"urn:btih:6d8b377e6ac53c4f1bc792f62f6b5ac0daa5cf88","amp;dn":"Sucktion+and+Ride","amp;tr":["udp%3A%2F%2Ftracker.leechers-paradise.org%3A6969","udp%3A%2F%2Fzer0day.ch%3A1337","udp%3A%2F%2Fopen.demonii.com%3A1337","udp%3A%2F%2Ftracker.coppersurfer.tk%3A6969","udp%3A%2F%2Fexodus.desync.com%3A6969"],"infoHash":"6d8b377e6ac53c4f1bc792f62f6b5ac0daa5cf88","infoHashBuffer":{"type":"Buffer","data":[109,139,55,126,106,197,60,79,27,199,146,246,47,107,90,192,218,165,207,136]},"announce":[],"urlList":[]}}