{"title":"Public Morals (2015) 1x06 [HDiTunes Ac3 Cas] By JBilbo","uid":13052065,"size":428756992,"categoryP":"video","categoryS":"tv_shows","magnet":"?xt=urn:btih:7e5510860c47d9b41a6f9e90af8c9eb6e0c9fa9c&amp;dn=Public+Morals+%282015%29+1x06+%5BHDiTunes+Ac3+Cas%5D+By+JBilbo&amp;tr=udp%3A%2F%2Ftracker.leechers-paradise.org%3A6969&amp;tr=udp%3A%2F%2Fzer0day.ch%3A1337&amp;tr=udp%3A%2F%2Fopen.demonii.com%3A1337&amp;tr=udp%3A%2F%2Ftracker.coppersurfer.tk%3A6969&amp;tr=udp%3A%2F%2Fexodus.desync.com%3A6969","seeders":0,"leechers":0,"uploader":"JBilbo","files":1,"time":1450629701,"description":"Título original    Public Morals (TV Series)\r\n\r\nAño    2015\r\n\r\nDuración    60 min.\r\n\r\nPaís  Estados Unidos\r\n\r\nDirector    Edward Burns\r\n\r\nGuión    Edward Burns\r\n\r\nFotografía    William Rexer\r\n\r\nReparto    Edward Burns, Michael Rapaport, Elizabeth Masucci, Katrina Bowden, Cormac Cullinane, Austin Stowell, Patrick Murney, Ruben Santiago-Hudson, Lyndon Smith, Keith Nobbs, Wass Stevens, Michele Hicks, Kevin Corrigan, Ray Wiederhold, Neal McDonough, Kaley Ronayne, Megan West, Lorraine Farris, Whitney Vance\r\n\r\nProductora    Amblin Television / Marlboro Road Gang Productions\r\n\r\nGénero    Serie de TV. Drama | Años 60. Neo-noir. Policíaco\r\n\r\n\r\n\r\nSinopsis    Serie de TV. 'Public Morals' se traslada hasta 1967 donde los policías de una conocida División de la ciudad de Nueva York se encuentran constantemente en una lucha entre la moralidad y el lado más oscuro de las tentaciones que derivan de todo tipo de vicios. La serie sigue a Terry Muldoon (Edward Burns), un policía consciente de la delgada línea que separa el decoro y la honestidad de la corrupción. Así, su objetivo será guiar a sus subordinados hacía el bien y combatir el oscuro mundo de la delincuencia y el vicio. (FILMAFFINITY)","torrent":{"xt":"urn:btih:7e5510860c47d9b41a6f9e90af8c9eb6e0c9fa9c","amp;dn":"Public+Morals+%282015%29+1x06+%5BHDiTunes+Ac3+Cas%5D+By+JBilbo","amp;tr":["udp%3A%2F%2Ftracker.leechers-paradise.org%3A6969","udp%3A%2F%2Fzer0day.ch%3A1337","udp%3A%2F%2Fopen.demonii.com%3A1337","udp%3A%2F%2Ftracker.coppersurfer.tk%3A6969","udp%3A%2F%2Fexodus.desync.com%3A6969"],"infoHash":"7e5510860c47d9b41a6f9e90af8c9eb6e0c9fa9c","infoHashBuffer":{"type":"Buffer","data":[126,85,16,134,12,71,217,180,26,111,158,144,175,140,158,182,224,201,250,156]},"announce":[],"urlList":[]}}