{"title":"[UNCENSORED]Pacopacomama - 011416_012 - Yumi Wajiro (å’ŒåŸŽè£•ç¾Ž)","uid":13313191,"size":2014044276,"categoryP":"porn","categoryS":"hd___movies","magnet":"?xt=urn:btih:845c0948c722ccdf0cf1e33fe1c93d6e985d4d00&amp;dn=%5BUNCENSORED%5DPacopacomama+-+011416_012+-+Yumi+Wajiro+%28%E5%92%8C%E5%9F%8E%E8%A3%95%E7%BE%8E%29&amp;tr=udp%3A%2F%2Ftracker.leechers-paradise.org%3A6969&amp;tr=udp%3A%2F%2Fzer0day.ch%3A1337&amp;tr=udp%3A%2F%2Fopen.demonii.com%3A1337&amp;tr=udp%3A%2F%2Ftracker.coppersurfer.tk%3A6969&amp;tr=udp%3A%2F%2Fexodus.desync.com%3A6969","seeders":0,"leechers":1,"uploader":"hunter534","files":1,"time":1453799624,"description":"\nTitle: Pacopacomama 011416_012 æ­£è£…ã—ãŸã‚‰ã€æŸãŠç¬‘ã„æ€ªç£ã®å¨˜ã«è¦‹ãˆã¦ããŸäººå¦»\r\nStarring: Yumi Wajiro (å’ŒåŸŽè£•ç¾Ž)\r\nAge: 28\r\nBody Size: B:84 W:58 H:84\r\nCategory: 20ä»£ å¾®ä¹³ ãƒã‚¤ãƒ–\r\nStudio: Pacopacomama\r\n\r\nCOVER+SCEENSHOT:\r\n \nhttp://ads-img.info/img-56a72a9707e54.html \r\n \nhttp://pop-img.info/img-56a72aa0b1bf2.html","torrent":{"xt":"urn:btih:845c0948c722ccdf0cf1e33fe1c93d6e985d4d00","amp;dn":"%5BUNCENSORED%5DPacopacomama+-+011416_012+-+Yumi+Wajiro+%28%E5%92%8C%E5%9F%8E%E8%A3%95%E7%BE%8E%29","amp;tr":["udp%3A%2F%2Ftracker.leechers-paradise.org%3A6969","udp%3A%2F%2Fzer0day.ch%3A1337","udp%3A%2F%2Fopen.demonii.com%3A1337","udp%3A%2F%2Ftracker.coppersurfer.tk%3A6969","udp%3A%2F%2Fexodus.desync.com%3A6969"],"infoHash":"845c0948c722ccdf0cf1e33fe1c93d6e985d4d00","infoHashBuffer":{"type":"Buffer","data":[132,92,9,72,199,34,204,223,12,241,227,63,225,201,61,110,152,93,77,0]},"announce":[],"urlList":[]}}