{"title":"[UNCENSORED]Muramura - 011216_337 - Kazue Nishito (è¥¿é–€å’Œæµ)","uid":13336108,"size":1599770396,"categoryP":"porn","categoryS":"hd___movies","magnet":"?xt=urn:btih:9f0c509a29a5a205f11579bb72e7ca11e31b6602&amp;dn=%5BUNCENSORED%5DMuramura+-+011216_337+-+Kazue+Nishito+%28%E8%A5%BF%E9%96%80%E5%92%8C%E6%81%B5%29&amp;tr=udp%3A%2F%2Ftracker.leechers-paradise.org%3A6969&amp;tr=udp%3A%2F%2Fzer0day.ch%3A1337&amp;tr=udp%3A%2F%2Fopen.demonii.com%3A1337&amp;tr=udp%3A%2F%2Ftracker.coppersurfer.tk%3A6969&amp;tr=udp%3A%2F%2Fexodus.desync.com%3A6969","seeders":0,"leechers":0,"uploader":"hunter534","files":1,"time":1453989735,"description":"Title: ãƒ ãƒ©ãƒ ãƒ© 011216_337 ã‚»ãƒ³ã‚ºãƒªé‘‘è³žã‚¢ãƒ«ãƒã‚¤ãƒˆï½žæ®‹æ¥­ä»£ãªã—ï¼ç”·ãªã—ï¼ä¸æ™¯æ°—ã ã‚‰ã‘ã®ï¼¯ï¼¬ãŒãƒã‚¤ãƒˆæ–™ã‚’å¼¾ã‚€ã¨è¨€ã‚ã‚Œä¸­å‡ºã—å³ï¼¯ï¼«ï¼ï½ž\r\nStarring: Kazue Nishito (è¥¿é–€å’Œæµ)\r\nCategory: OL ç”Ÿãƒãƒ¡ ä¸­å‡ºã— ã‚ªãƒŠãƒ‹ãƒ¼ ãƒ•ã‚§ãƒ©ãƒã‚ª ç´ äºº\r\nStudio: Muramura\r\n\r\n\r\nCOVER+SCEENSHOT\r\n \nhttp://ads-img.info/img-56aa113f9fce4.html \r\n \nhttp://pop-img.info/img-56aa11495fe69.html","torrent":{"xt":"urn:btih:9f0c509a29a5a205f11579bb72e7ca11e31b6602","amp;dn":"%5BUNCENSORED%5DMuramura+-+011216_337+-+Kazue+Nishito+%28%E8%A5%BF%E9%96%80%E5%92%8C%E6%81%B5%29","amp;tr":["udp%3A%2F%2Ftracker.leechers-paradise.org%3A6969","udp%3A%2F%2Fzer0day.ch%3A1337","udp%3A%2F%2Fopen.demonii.com%3A1337","udp%3A%2F%2Ftracker.coppersurfer.tk%3A6969","udp%3A%2F%2Fexodus.desync.com%3A6969"],"infoHash":"9f0c509a29a5a205f11579bb72e7ca11e31b6602","infoHashBuffer":{"type":"Buffer","data":[159,12,80,154,41,165,162,5,241,21,121,187,114,231,202,17,227,27,102,2]},"announce":[],"urlList":[]}}