{"title":"Mind Control - Bed and Breakfast","uid":13441229,"size":699663171,"categoryP":"porn","categoryS":"movies","magnet":"?xt=urn:btih:af591dee898feb2f53ab26c4618af812da7445b4&amp;dn=Mind+Control+-+Bed+and+Breakfast&amp;tr=udp%3A%2F%2Ftracker.leechers-paradise.org%3A6969&amp;tr=udp%3A%2F%2Fzer0day.ch%3A1337&amp;tr=udp%3A%2F%2Fopen.demonii.com%3A1337&amp;tr=udp%3A%2F%2Ftracker.coppersurfer.tk%3A6969&amp;tr=udp%3A%2F%2Fexodus.desync.com%3A6969","seeders":0,"leechers":4,"uploader":"samualgenamc","files":1,"time":1454706075,"description":"Mind Control - Bed and Breakfast\r\n\r\nStarring Eva Notty * Seth Dickens\r\nJanet has a gentleman caller who seems to know all about her… so why doesn’t she remember any thing about him?\r\n40 min\r\nBoy/Girl * Male Dominant * Busty * Shot in HD","torrent":{"xt":"urn:btih:af591dee898feb2f53ab26c4618af812da7445b4","amp;dn":"Mind+Control+-+Bed+and+Breakfast","amp;tr":["udp%3A%2F%2Ftracker.leechers-paradise.org%3A6969","udp%3A%2F%2Fzer0day.ch%3A1337","udp%3A%2F%2Fopen.demonii.com%3A1337","udp%3A%2F%2Ftracker.coppersurfer.tk%3A6969","udp%3A%2F%2Fexodus.desync.com%3A6969"],"infoHash":"af591dee898feb2f53ab26c4618af812da7445b4","infoHashBuffer":{"type":"Buffer","data":[175,89,29,238,137,143,235,47,83,171,38,196,97,138,248,18,218,116,69,180]},"announce":[],"urlList":[]}}