{"title":"HandsonHardcore: Amirah - Delighted to be Filled XXX [264]","uid":13474435,"size":793523970,"categoryP":"porn","categoryS":"other","magnet":"?xt=urn:btih:b441dd41eed6e71b300fa192ea1eb64fc15c91e0&amp;dn=HandsonHardcore%3A+Amirah+-+Delighted+to+be+Filled+XXX+%5B264%5D&amp;tr=udp%3A%2F%2Ftracker.leechers-paradise.org%3A6969&amp;tr=udp%3A%2F%2Fzer0day.ch%3A1337&amp;tr=udp%3A%2F%2Fopen.demonii.com%3A1337&amp;tr=udp%3A%2F%2Ftracker.coppersurfer.tk%3A6969&amp;tr=udp%3A%2F%2Fexodus.desync.com%3A6969","seeders":0,"leechers":1,"uploader":"ImgSnaps","files":3,"time":1454992854,"description":"Screenshots:\r\n \nhttp://imgsnaps.com/image/GYs\r\n \nhttp://imgsnaps.com/image/GYu","torrent":{"xt":"urn:btih:b441dd41eed6e71b300fa192ea1eb64fc15c91e0","amp;dn":"HandsonHardcore%3A+Amirah+-+Delighted+to+be+Filled+XXX+%5B264%5D","amp;tr":["udp%3A%2F%2Ftracker.leechers-paradise.org%3A6969","udp%3A%2F%2Fzer0day.ch%3A1337","udp%3A%2F%2Fopen.demonii.com%3A1337","udp%3A%2F%2Ftracker.coppersurfer.tk%3A6969","udp%3A%2F%2Fexodus.desync.com%3A6969"],"infoHash":"b441dd41eed6e71b300fa192ea1eb64fc15c91e0","infoHashBuffer":{"type":"Buffer","data":[180,65,221,65,238,214,231,27,48,15,161,146,234,30,182,79,193,92,145,224]},"announce":[],"urlList":[]}}