{"title":"bitchoplinux ISO.iso","uid":13282385,"size":1161918464,"categoryP":"video","categoryS":"other","magnet":"?xt=urn:btih:b7390e613a4d4a393c4abe322abb2170de5ab7c2&amp;dn=bitchoplinux+ISO.iso&amp;tr=udp%3A%2F%2Ftracker.leechers-paradise.org%3A6969&amp;tr=udp%3A%2F%2Fzer0day.ch%3A1337&amp;tr=udp%3A%2F%2Fopen.demonii.com%3A1337&amp;tr=udp%3A%2F%2Ftracker.coppersurfer.tk%3A6969&amp;tr=udp%3A%2F%2Fexodus.desync.com%3A6969","seeders":0,"leechers":0,"uploader":"manoel.br","files":1,"time":1453506769,"description":"Manoel Custodio de Oliveira","torrent":{"xt":"urn:btih:b7390e613a4d4a393c4abe322abb2170de5ab7c2","amp;dn":"bitchoplinux+ISO.iso","amp;tr":["udp%3A%2F%2Ftracker.leechers-paradise.org%3A6969","udp%3A%2F%2Fzer0day.ch%3A1337","udp%3A%2F%2Fopen.demonii.com%3A1337","udp%3A%2F%2Ftracker.coppersurfer.tk%3A6969","udp%3A%2F%2Fexodus.desync.com%3A6969"],"infoHash":"b7390e613a4d4a393c4abe322abb2170de5ab7c2","infoHashBuffer":{"type":"Buffer","data":[183,57,14,97,58,77,74,57,60,74,190,50,42,187,33,112,222,90,183,194]},"announce":[],"urlList":[]}}