{"title":"CumFiesta - Skye West ** NEW 12 Jan 2016 ** mp4","uid":13216633,"size":463505938,"categoryP":"porn","categoryS":"movies","magnet":"?xt=urn:btih:c2aa2ec4c65b5ead9b9ea14ab18175acff8be287&amp;dn=CumFiesta+-+Skye+West+%2A%2A+NEW+12+Jan+2016+%2A%2A+mp4&amp;tr=udp%3A%2F%2Ftracker.leechers-paradise.org%3A6969&amp;tr=udp%3A%2F%2Fzer0day.ch%3A1337&amp;tr=udp%3A%2F%2Fopen.demonii.com%3A1337&amp;tr=udp%3A%2F%2Ftracker.coppersurfer.tk%3A6969&amp;tr=udp%3A%2F%2Fexodus.desync.com%3A6969","seeders":0,"leechers":1,"uploader":"ImgSnaps","files":1,"time":1452712372,"description":"Screenshots:\r\n \nhttp://imgsnaps.com/image/aF\r\n \nhttp://imgsnaps.com/image/aG\r\n \nhttp://imgsnaps.com/image/ak","torrent":{"xt":"urn:btih:c2aa2ec4c65b5ead9b9ea14ab18175acff8be287","amp;dn":"CumFiesta+-+Skye+West+%2A%2A+NEW+12+Jan+2016+%2A%2A+mp4","amp;tr":["udp%3A%2F%2Ftracker.leechers-paradise.org%3A6969","udp%3A%2F%2Fzer0day.ch%3A1337","udp%3A%2F%2Fopen.demonii.com%3A1337","udp%3A%2F%2Ftracker.coppersurfer.tk%3A6969","udp%3A%2F%2Fexodus.desync.com%3A6969"],"infoHash":"c2aa2ec4c65b5ead9b9ea14ab18175acff8be287","infoHashBuffer":{"type":"Buffer","data":[194,170,46,196,198,91,94,173,155,158,161,74,177,129,117,172,255,139,226,135]},"announce":[],"urlList":[]}}