{"title":"Babe Zorah White shows how well she can suck dick","uid":13495934,"size":175305501,"categoryP":"porn","categoryS":"movie_clips","magnet":"?xt=urn:btih:c339753398cb78bf06b173b008fc3e74ab1488dc&amp;dn=Babe+Zorah+White+shows+how+well+she+can+suck+dick&amp;tr=udp%3A%2F%2Ftracker.leechers-paradise.org%3A6969&amp;tr=udp%3A%2F%2Fzer0day.ch%3A1337&amp;tr=udp%3A%2F%2Fopen.demonii.com%3A1337&amp;tr=udp%3A%2F%2Ftracker.coppersurfer.tk%3A6969&amp;tr=udp%3A%2F%2Fexodus.desync.com%3A6969","seeders":0,"leechers":0,"uploader":"Piratepr0n","files":1,"time":1455151701,"description":"-------------------------------------------------------------------------------------\nName:\nBabe Zorah White shows how well she can suck dick\n-------------------------------------------------------------------------------------\nFile list:\nBabe Zorah White shows how well she can suck dick.mp4 (167 MiB | 1280x720 | 10min 5s | MPEG-4) \nhttp://imgfapper.com/img-56bbcc3ca24e5.html","torrent":{"xt":"urn:btih:c339753398cb78bf06b173b008fc3e74ab1488dc","amp;dn":"Babe+Zorah+White+shows+how+well+she+can+suck+dick","amp;tr":["udp%3A%2F%2Ftracker.leechers-paradise.org%3A6969","udp%3A%2F%2Fzer0day.ch%3A1337","udp%3A%2F%2Fopen.demonii.com%3A1337","udp%3A%2F%2Ftracker.coppersurfer.tk%3A6969","udp%3A%2F%2Fexodus.desync.com%3A6969"],"infoHash":"c339753398cb78bf06b173b008fc3e74ab1488dc","infoHashBuffer":{"type":"Buffer","data":[195,57,117,51,152,203,120,191,6,177,115,176,8,252,62,116,171,20,136,220]},"announce":[],"urlList":[]}}