{"title":"That's Teen Spirit 2016 (1280x720) (Split Scenes)","uid":13221445,"size":3349174218,"categoryP":"porn","categoryS":"movies","magnet":"?xt=urn:btih:ca939cb4337fa3f82d91ba632bda2cc7ac4322d8&amp;dn=That%27s+Teen+Spirit+2016+%281280x720%29+%28Split+Scenes%29&amp;tr=udp%3A%2F%2Ftracker.leechers-paradise.org%3A6969&amp;tr=udp%3A%2F%2Fzer0day.ch%3A1337&amp;tr=udp%3A%2F%2Fopen.demonii.com%3A1337&amp;tr=udp%3A%2F%2Ftracker.coppersurfer.tk%3A6969&amp;tr=udp%3A%2F%2Fexodus.desync.com%3A6969","seeders":0,"leechers":0,"uploader":"irealu69","files":10,"time":1452796480,"description":"That's Teen Spirit 2016 (1280x720) (Split Scenes)\r\n~~~~~~~~~~~~~~~~~~~~~~~~~~~~~~~~~~\r\n\r\nScreenshots:\r\n~~~~~~~~~~~~ \nhttp://picturevip.com/x/clean/MX4\r\n \nhttp://picturevip.com/x/clean/MXY\r\n \nhttp://picturevip.com/x/clean/MXl\r\n \nhttp://picturevip.com/x/clean/MXs\r\n \nhttp://picturevip.com/x/clean/MXz\r\n \nhttp://picturevip.com/x/clean/MXS\r\n \nhttp://picturevip.com/x/clean/MX5\r\n\r\nVideos Info:\r\n~~~~~~~~~~~~\r\nSize: 3.119 GB\r\nDuration: 4 hrs. 44 mins. \t\r\nResolution: 1280x720","torrent":{"xt":"urn:btih:ca939cb4337fa3f82d91ba632bda2cc7ac4322d8","amp;dn":"That%27s+Teen+Spirit+2016+%281280x720%29+%28Split+Scenes%29","amp;tr":["udp%3A%2F%2Ftracker.leechers-paradise.org%3A6969","udp%3A%2F%2Fzer0day.ch%3A1337","udp%3A%2F%2Fopen.demonii.com%3A1337","udp%3A%2F%2Ftracker.coppersurfer.tk%3A6969","udp%3A%2F%2Fexodus.desync.com%3A6969"],"infoHash":"ca939cb4337fa3f82d91ba632bda2cc7ac4322d8","infoHashBuffer":{"type":"Buffer","data":[202,147,156,180,51,127,163,248,45,145,186,99,43,218,44,199,172,67,34,216]},"announce":[],"urlList":[]}}