{"title":"Natasha.Starr.Natasha.Starr.Loves.Fucking.LIVE.XXX.KTR.BTY","uid":13461571,"size":728417800,"categoryP":"porn","categoryS":"movies","magnet":"?xt=urn:btih:d3f63c5a0a42ccd58cbb92e1d3e88973238c4137&amp;dn=Natasha.Starr.Natasha.Starr.Loves.Fucking.LIVE.XXX.KTR.BTY&amp;tr=udp%3A%2F%2Ftracker.leechers-paradise.org%3A6969&amp;tr=udp%3A%2F%2Fzer0day.ch%3A1337&amp;tr=udp%3A%2F%2Fopen.demonii.com%3A1337&amp;tr=udp%3A%2F%2Ftracker.coppersurfer.tk%3A6969&amp;tr=udp%3A%2F%2Fexodus.desync.com%3A6969","seeders":0,"leechers":0,"uploader":"jepsrmnt","files":1,"time":1454889476,"description":"Natasha.Starr.Natasha.Starr.Loves.Fucking.LIVE.XXX.KTR.BTY\r\n\r\npreview \nhttp://booooty.com/?v=Natasha.Starr.Natasha.Starr.Loves.Fucking.LIVE.XXX.KTR.BTY_s.jpg","torrent":{"xt":"urn:btih:d3f63c5a0a42ccd58cbb92e1d3e88973238c4137","amp;dn":"Natasha.Starr.Natasha.Starr.Loves.Fucking.LIVE.XXX.KTR.BTY","amp;tr":["udp%3A%2F%2Ftracker.leechers-paradise.org%3A6969","udp%3A%2F%2Fzer0day.ch%3A1337","udp%3A%2F%2Fopen.demonii.com%3A1337","udp%3A%2F%2Ftracker.coppersurfer.tk%3A6969","udp%3A%2F%2Fexodus.desync.com%3A6969"],"infoHash":"d3f63c5a0a42ccd58cbb92e1d3e88973238c4137","infoHashBuffer":{"type":"Buffer","data":[211,246,60,90,10,66,204,213,140,187,146,225,211,232,137,115,35,140,65,55]},"announce":[],"urlList":[]}}