{"title":"Sweet ass hit hard","uid":13037005,"size":132707372,"categoryP":"porn","categoryS":"movie_clips","magnet":"?xt=urn:btih:d423c887c214cd1ec522f7d25ecb99b4308a495a&amp;dn=Sweet+ass+hit+hard&amp;tr=udp%3A%2F%2Ftracker.leechers-paradise.org%3A6969&amp;tr=udp%3A%2F%2Fzer0day.ch%3A1337&amp;tr=udp%3A%2F%2Fopen.demonii.com%3A1337&amp;tr=udp%3A%2F%2Ftracker.coppersurfer.tk%3A6969&amp;tr=udp%3A%2F%2Fexodus.desync.com%3A6969","seeders":0,"leechers":0,"uploader":"demonoidt","files":1,"time":1450486990,"description":"Samples\r\n \nhttp://adultwallpapers.co.in/sweet-ass-hit-hard/\r\n \nhttp://adultwallpapers.co.in/sweet-ass-hit-hard-2/\r\n \nhttp://adultwallpapers.co.in/sweet-ass-hit-hard-3/\r\n \nhttp://demonoid.co/2015/12/18/sweet-ass-hit-hard/","torrent":{"xt":"urn:btih:d423c887c214cd1ec522f7d25ecb99b4308a495a","amp;dn":"Sweet+ass+hit+hard","amp;tr":["udp%3A%2F%2Ftracker.leechers-paradise.org%3A6969","udp%3A%2F%2Fzer0day.ch%3A1337","udp%3A%2F%2Fopen.demonii.com%3A1337","udp%3A%2F%2Ftracker.coppersurfer.tk%3A6969","udp%3A%2F%2Fexodus.desync.com%3A6969"],"infoHash":"d423c887c214cd1ec522f7d25ecb99b4308a495a","infoHashBuffer":{"type":"Buffer","data":[212,35,200,135,194,20,205,30,197,34,247,210,94,203,153,180,48,138,73,90]},"announce":[],"urlList":[]}}