{"title":"Cosmid.16.02.08.Scarlett.Jo.XXX.720p.MP4-KTR[N1C]","uid":13464834,"size":718981016,"categoryP":"porn","categoryS":"other","magnet":"?xt=urn:btih:db1449257d318863c8f34e05472ca3c6b307ad4f&amp;dn=Cosmid.16.02.08.Scarlett.Jo.XXX.720p.MP4-KTR%5BN1C%5D&amp;tr=udp%3A%2F%2Ftracker.leechers-paradise.org%3A6969&amp;tr=udp%3A%2F%2Fzer0day.ch%3A1337&amp;tr=udp%3A%2F%2Fopen.demonii.com%3A1337&amp;tr=udp%3A%2F%2Ftracker.coppersurfer.tk%3A6969&amp;tr=udp%3A%2F%2Fexodus.desync.com%3A6969","seeders":0,"leechers":1,"uploader":"juggs99","files":2,"time":1454917580,"description":"\nCosmid.16.02.08.Scarlett.Jo.XXX.720p.MP4-KTR \r\n\n\n[Format]:    MPEG-4\n[Duration]:    12mn 12s\n[Original width]:    1 280 pixels\n[Resolution]:  1 248 x 702 pixels\n[Original height]:    720 pixels\n[Display aspect ratio]:    16:9\n[Frame rate mode]:    Constant\n[Frame rate]:    29.970 fps\n\r\n\n#N1C -&gt; To avoid fakes, ALWAYS check that the torrent was added by NO1CARES\r \nhttp://extratorrent.cc/\r\n\n\nHelp us by donating with Bitcoin: 1XeH1kKXWYbzZcFHokGiZ4d3MWW5WyXzU\r\n\nScreens...\r \nhttp://HotImage.uk/img-56b8397573efd.html\r \nhttp://HotImage.uk/img-56b839757daf3.html\r \nhttp://HotImage.uk/img-56b8397588ce1.html\r \nhttp://HotImage.uk/img-56b839759215e.html","torrent":{"xt":"urn:btih:db1449257d318863c8f34e05472ca3c6b307ad4f","amp;dn":"Cosmid.16.02.08.Scarlett.Jo.XXX.720p.MP4-KTR%5BN1C%5D","amp;tr":["udp%3A%2F%2Ftracker.leechers-paradise.org%3A6969","udp%3A%2F%2Fzer0day.ch%3A1337","udp%3A%2F%2Fopen.demonii.com%3A1337","udp%3A%2F%2Ftracker.coppersurfer.tk%3A6969","udp%3A%2F%2Fexodus.desync.com%3A6969"],"infoHash":"db1449257d318863c8f34e05472ca3c6b307ad4f","infoHashBuffer":{"type":"Buffer","data":[219,20,73,37,125,49,136,99,200,243,78,5,71,44,163,198,179,7,173,79]},"announce":[],"urlList":[]}}