{"title":"German girl gets fucked","uid":14634958,"size":106239336,"categoryP":"porn","categoryS":"movie_clips","magnet":"?xt=urn:btih:ed4b8712710b10bf3337f8b423c85e0d27cd2f4d&amp;dn=German+girl+gets+fucked&amp;tr=udp%3A%2F%2Ftracker.leechers-paradise.org%3A6969&amp;tr=udp%3A%2F%2Fzer0day.ch%3A1337&amp;tr=udp%3A%2F%2Fopen.demonii.com%3A1337&amp;tr=udp%3A%2F%2Ftracker.coppersurfer.tk%3A6969&amp;tr=udp%3A%2F%2Fexodus.desync.com%3A6969","seeders":0,"leechers":0,"uploader":"Piratepr0n","files":1,"time":1463434718,"description":"-------------------------------------------------------------------------------------\nName:\nGerman girl gets fucked\n-------------------------------------------------------------------------------------\nFile list:\nGerman girl gets fucked.mpg (101 MiB | 352x288 | 10min 5s | MPEG-PS) \nhttp://imgfapper.com/img-573a21b95dddb.html","torrent":{"xt":"urn:btih:ed4b8712710b10bf3337f8b423c85e0d27cd2f4d","amp;dn":"German+girl+gets+fucked","amp;tr":["udp%3A%2F%2Ftracker.leechers-paradise.org%3A6969","udp%3A%2F%2Fzer0day.ch%3A1337","udp%3A%2F%2Fopen.demonii.com%3A1337","udp%3A%2F%2Ftracker.coppersurfer.tk%3A6969","udp%3A%2F%2Fexodus.desync.com%3A6969"],"infoHash":"ed4b8712710b10bf3337f8b423c85e0d27cd2f4d","infoHashBuffer":{"type":"Buffer","data":[237,75,135,18,113,11,16,191,51,55,248,180,35,200,94,13,39,205,47,77]},"announce":[],"urlList":[]}}