{"title":"[CzechCouples] Czech Couples (Episode 17) [XXX]","uid":13460895,"size":226274592,"categoryP":"porn","categoryS":"other","magnet":"?xt=urn:btih:f7afca94cbc509a13976c1c480482e515a1199eb&amp;dn=%5BCzechCouples%5D+Czech+Couples+%28Episode+17%29+%5BXXX%5D&amp;tr=udp%3A%2F%2Ftracker.leechers-paradise.org%3A6969&amp;tr=udp%3A%2F%2Fzer0day.ch%3A1337&amp;tr=udp%3A%2F%2Fopen.demonii.com%3A1337&amp;tr=udp%3A%2F%2Ftracker.coppersurfer.tk%3A6969&amp;tr=udp%3A%2F%2Fexodus.desync.com%3A6969","seeders":0,"leechers":1,"uploader":"ImgSnaps","files":3,"time":1454887000,"description":"Screenshots:\r\n \nhttp://imgsnaps.com/image/Gt9\r\n\r\nCategory: Group, BJ, Facial, POV, Hardcore, All Sex\r\n\r\nCast: Amateur","torrent":{"xt":"urn:btih:f7afca94cbc509a13976c1c480482e515a1199eb","amp;dn":"%5BCzechCouples%5D+Czech+Couples+%28Episode+17%29+%5BXXX%5D","amp;tr":["udp%3A%2F%2Ftracker.leechers-paradise.org%3A6969","udp%3A%2F%2Fzer0day.ch%3A1337","udp%3A%2F%2Fopen.demonii.com%3A1337","udp%3A%2F%2Ftracker.coppersurfer.tk%3A6969","udp%3A%2F%2Fexodus.desync.com%3A6969"],"infoHash":"f7afca94cbc509a13976c1c480482e515a1199eb","infoHashBuffer":{"type":"Buffer","data":[247,175,202,148,203,197,9,161,57,118,193,196,128,72,46,81,90,17,153,235]},"announce":[],"urlList":[]}}