{"title":"My.First.Sex.Teacher.Crystal.Rae.XXX.KTR.BTY","uid":13442823,"size":1221668991,"categoryP":"porn","categoryS":"movies","magnet":"?xt=urn:btih:fb23b66d12c5eb075f732af06933726bb6826b4d&amp;dn=My.First.Sex.Teacher.Crystal.Rae.XXX.KTR.BTY&amp;tr=udp%3A%2F%2Ftracker.leechers-paradise.org%3A6969&amp;tr=udp%3A%2F%2Fzer0day.ch%3A1337&amp;tr=udp%3A%2F%2Fopen.demonii.com%3A1337&amp;tr=udp%3A%2F%2Ftracker.coppersurfer.tk%3A6969&amp;tr=udp%3A%2F%2Fexodus.desync.com%3A6969","seeders":0,"leechers":1,"uploader":"jepsrmnt","files":1,"time":1454718757,"description":"My.First.Sex.Teacher.Crystal.Rae.XXX.KTR.BTY\r\n\r\npreview \nhttp://booooty.com/?v=My.First.Sex.Teacher.Crystal.Rae.XXX.KTR.BTY_s.jpg","torrent":{"xt":"urn:btih:fb23b66d12c5eb075f732af06933726bb6826b4d","amp;dn":"My.First.Sex.Teacher.Crystal.Rae.XXX.KTR.BTY","amp;tr":["udp%3A%2F%2Ftracker.leechers-paradise.org%3A6969","udp%3A%2F%2Fzer0day.ch%3A1337","udp%3A%2F%2Fopen.demonii.com%3A1337","udp%3A%2F%2Ftracker.coppersurfer.tk%3A6969","udp%3A%2F%2Fexodus.desync.com%3A6969"],"infoHash":"fb23b66d12c5eb075f732af06933726bb6826b4d","infoHashBuffer":{"type":"Buffer","data":[251,35,182,109,18,197,235,7,95,115,42,240,105,51,114,107,182,130,107,77]},"announce":[],"urlList":[]}}